LICENSE.txt
MANIFEST.in
README.md
requirements.txt
setup.cfg
setup.py
sematch/__init__.py
sematch/application.py
sematch/download.py
sematch/evaluation.py
sematch/nlp.py
sematch/utility.py
sematch.egg-info/PKG-INFO
sematch.egg-info/SOURCES.txt
sematch.egg-info/dependency_links.txt
sematch.egg-info/requires.txt
sematch.egg-info/top_level.txt
sematch/dataset/aspect/.DS_Store
sematch/dataset/aspect/data.txt
sematch/dataset/wordsim/.DS_Store
sematch/dataset/wordsim/README.md
sematch/dataset/wordsim/graph_mc.txt
sematch/dataset/wordsim/graph_rg.txt
sematch/dataset/wordsim/graph_simlex.txt
sematch/dataset/wordsim/graph_ws353-sim.txt
sematch/dataset/wordsim/graph_ws353.txt
sematch/dataset/wordsim/noun_mc.txt
sematch/dataset/wordsim/noun_rg.txt
sematch/dataset/wordsim/noun_simlex.txt
sematch/dataset/wordsim/noun_ws353-sim.txt
sematch/dataset/wordsim/noun_ws353.txt
sematch/dataset/wordsim/rg65_EN-ES.txt
sematch/dataset/wordsim/rg65_spanish.txt
sematch/dataset/wordsim/type_mc.txt
sematch/dataset/wordsim/type_rg.txt
sematch/dataset/wordsim/type_simlex.txt
sematch/dataset/wordsim/type_ws353-sim.txt
sematch/dataset/wordsim/type_ws353.txt
sematch/dataset/wordsim/results/graph_mc-jcn.txt
sematch/dataset/wordsim/results/graph_mc-lch.txt
sematch/dataset/wordsim/results/graph_mc-li.txt
sematch/dataset/wordsim/results/graph_mc-lin.txt
sematch/dataset/wordsim/results/graph_mc-path.txt
sematch/dataset/wordsim/results/graph_mc-res.txt
sematch/dataset/wordsim/results/graph_mc-res_graph.txt
sematch/dataset/wordsim/results/graph_mc-wup.txt
sematch/dataset/wordsim/results/graph_rg-jcn.txt
sematch/dataset/wordsim/results/graph_rg-lch.txt
sematch/dataset/wordsim/results/graph_rg-li.txt
sematch/dataset/wordsim/results/graph_rg-lin.txt
sematch/dataset/wordsim/results/graph_rg-path.txt
sematch/dataset/wordsim/results/graph_rg-res.txt
sematch/dataset/wordsim/results/graph_rg-res_graph.txt
sematch/dataset/wordsim/results/graph_rg-wup.txt
sematch/dataset/wordsim/results/graph_simlex-jcn.txt
sematch/dataset/wordsim/results/graph_simlex-lch.txt
sematch/dataset/wordsim/results/graph_simlex-li.txt
sematch/dataset/wordsim/results/graph_simlex-lin.txt
