Metadata-Version: 1.1
Name: sematch
Version: 1.0.4
Summary: Semantic similarity framework for knowledge graphs
Home-page: https://github.com/gsi-upm/sematch
Author: Ganggao Zhu
Author-email: gzhu@dit.upm.es
License: Apache 2.0
Keywords: semantic similarity,taxonomy,knowledge graph,semantic analysis,knowledge base,WordNet,DBpedia,YAGO,ontology
Platform: UNKNOWN
Classifier: Development Status :: 5 - Production/Stable
Classifier: Intended Audience :: Science/Research
Classifier: Operating System :: OS Independent
Classifier: Programming Language :: Python :: 2.7
Classifier: Topic :: Software Development :: Libraries
